hy_tools-1.6.0.dist-info/licenses/LICENSE.txt
hytools/__init__.py
hytools/base.py
hytools/brdf/__init__.py
hytools/brdf/brdf.py
hytools/brdf/flex.py
hytools/brdf/kernels.py
hytools/brdf/local.py
hytools/brdf/universal.py
hytools/glint/__init__.py
hytools/glint/gao_2021.py
hytools/glint/glint.py
hytools/glint/hedley_2005.py
hytools/glint/hochberg_2003.py
hytools/io/__init__.py
hytools/io/envi.py
hytools/io/neon.py
hytools/io/netcdf.py
hytools/masks/__init__.py
hytools/masks/calc_apply.py
hytools/masks/cloud.py
hytools/masks/masks.py
hytools/misc/__init__.py
hytools/misc/misc.py
hytools/plotting/__init__.py
hytools/plotting/brdf_diagnostics.py
hytools/topo/__init__.py
hytools/topo/c.py
hytools/topo/cosine.py
hytools/topo/modminn.py
hytools/topo/scs.py
hytools/topo/scsc.py
hytools/topo/topo.py
hytools/transform/__init__.py
hytools/transform/resampling.py
hy_tools-1.6.0.dist-info/METADATA
hy_tools-1.6.0.dist-info/WHEEL
hy_tools-1.6.0.dist-info/top_level.txt
hy_tools-1.6.0.dist-info/RECORD
