Metadata-Version: 2.4
Name: hy-tools
Version: 1.6.0
Summary: HyTools: Hyperspectral image processing library
Home-page: https://github.com/EnSpec/hytools
Author: Adam Chlus, Zhiwei Ye, Ting Zheng, Natalie Queally, Evan Greenberg and Philip Townsend
Author-email: Adam Chlus <adam.chlus@jpl.nasa.gov>, Zhiwei Ye <ye6@wisc.edu>, Ting Zheng <tzheng39@wisc.edu>, Natalie Queally <nqueally@ucla.edu>, Evan Greenberg <egreenberg@ucsb.edu>, Philip Townsend <ptownsend@wisc.edu>
License-Expression: GPL-3.0-only
Project-URL: Homepage, https://github.com/EnSpec/hytools
Project-URL: Documentation, https://hytools.readthedocs.io/en/latest/
Project-URL: Repository, https://github.com/EnSpec/hytools.git
Keywords: imaging spectroscopy,hyperspectral,remote sensing,BRDF correction,glint correction,topographic correction,brightness normalization
Classifier: Programming Language :: Python
Requires-Python: >3.9
License-File: LICENSE.txt
Requires-Dist: h5py
Requires-Dist: h5netcdf
Requires-Dist: matplotlib
Requires-Dist: numpy
Requires-Dist: pandas
Requires-Dist: ray
Requires-Dist: scikit-learn
Requires-Dist: scipy
Dynamic: author
Dynamic: home-page
Dynamic: license-file
Dynamic: requires-python
